{
    "type": "invoice",
    "invoice_number": "FAC-20250320-0050",
    "issue_date": "2025-03-20",
    "supplier": {
        "name": "Dupuy",
        "siret": "71060720390588",
        "tva": "FR83432714751",
        "address": null
    },
    "client": {
        "name": "Guy-Gérard Ribeiro",
        "address": "72, rue de Rolland, 80587 Sainte Lucy"
    },
    "items": [
        {
            "description": "Victime sentiment salle",
            "quantity": 6,
            "unit_price_ht": 428.0,
            "total_ht": 2568.0
        },
        {
            "description": "Fine qui bientét cesse",
            "quantity": 2,
            "unit_price_ht": 196.06,
            "total_ht": 392.12
        }
    ],
    "tva_rate": 0.4,
    "total_ht": 2960.12,
    "total_tva": 1184.05,
    "total_ttc": 4144.17,
    "labels": {
        "is_tva_incoherent": false
    },
    "_source_ocr": "FAC-20250320-0050.json"
}